.gitignore
CHANGES.txt
README.md
setup.py
djinn_announcements/__init__.py
djinn_announcements/admin.py
djinn_announcements/search_indexes.py
djinn_announcements/settings.py
djinn_announcements/urls.py
djinn_announcements.egg-info/PKG-INFO
djinn_announcements.egg-info/SOURCES.txt
djinn_announcements.egg-info/dependency_links.txt
djinn_announcements.egg-info/entry_points.txt
djinn_announcements.egg-info/not-zip-safe
djinn_announcements.egg-info/requires.txt
djinn_announcements.egg-info/top_level.txt
djinn_announcements/forms/__init__.py
djinn_announcements/forms/announcement.py
djinn_announcements/forms/announcementupdate.py
djinn_announcements/forms/serviceannouncement.py
djinn_announcements/locale/en_EN/LC_MESSAGES/django.po
djinn_announcements/locale/nl_NL/LC_MESSAGES/django.po
djinn_announcements/management/__init__.py
djinn_announcements/models/__init__.py
djinn_announcements/models/announcement.py
djinn_announcements/models/announcementupdate.py
djinn_announcements/models/serviceannouncement.py
djinn_announcements/static/css/djinn_announcements.css
djinn_announcements/static/js/djinn_announcements.js
djinn_announcements/templates/djinn_announcements/announcement_detail.html
djinn_announcements/templates/djinn_announcements/announcement_detail_modal.html
djinn_announcements/templates/djinn_announcements/serviceannouncement_add.html
djinn_announcements/templates/djinn_announcements/serviceannouncement_detail.html
djinn_announcements/templates/djinn_announcements/serviceannouncement_detail_modal.html
djinn_announcements/templates/djinn_announcements/serviceannouncement_edit.html
djinn_announcements/templates/djinn_announcements/serviceannouncement_my_item.html
djinn_announcements/templates/djinn_announcements/serviceannouncement_overview_item.html
djinn_announcements/templates/djinn_announcements/snippets/announcement.html
djinn_announcements/templates/djinn_announcements/snippets/announcements.html
djinn_announcements/templates/djinn_announcements/snippets/announcements_viewlet.html
djinn_announcements/templates/djinn_announcements/snippets/announcementupdate.html
djinn_announcements/templates/djinn_announcements/snippets/priority_announcements_viewlet.html
djinn_announcements/templates/djinn_announcements/snippets/serviceannouncements_viewlet.html
